[
  {
    "year": 2023,
    "month": 3,
    "goods": [
      {
        "id": 1,
        "name": "Strawberry Delight Cupcake",
        "imgUrl": "/images/goods1.png",
        "amount": 10223301
      },
      {
        "id": 4,
        "name": "Berrylicious Tart",
        "imgUrl": "/images/goods4.png",
        "amount": 987373
      },
      {
        "id": 6,
        "name": "Blossom Bliss Macarons",
        "imgUrl": "/images/goods6.png",
        "amount": 876698
      }
    ],
    "totalAmount": 18223301,
    "id": 4
  },
  {
    "year": 2023,
    "month": 2,
    "goods": [
      {
        "id": 1,
        "name": "Strawberry Delight Cupcake",
        "imgUrl": "/images/goods1.png",
        "amount": 10223301
      },
      {
        "id": 3,
        "name": "Choco-Heaven Pancake Delight",
        "imgUrl": "/images/goods3.png",
        "amount": 987373
      },
      {
        "id": 5,
        "name": "Mocha Cookie Cupcake",
        "imgUrl": "/images/goods5.png",
        "amount": 876698
      }
    ],
    "totalAmount": 18223301,
    "id": 3
  },
  {
    "year": 2023,
    "month": 1,
    "goods": [
      {
        "id": 7,
        "name": "Triple Berry Yogurt Delight",
        "imgUrl": "/images/goods7.png",
        "amount": 10223301
      },
      {
        "id": 9,
        "name": "Strawberry Panna Bliss",
        "imgUrl": "/images/goods9.png",
        "amount": 987373
      },
      {
        "id": 2,
        "name": "Coffee Bliss Berry Cake",
        "imgUrl": "/images/goods2.png",
        "amount": 876698
      }
    ],
    "totalAmount": 18223301,
    "id": 2
  },
  {
    "year": 2022,
    "month": 12,
    "goods": [
      {
        "id": 5,
        "name": "Mocha Cookie Cupcake",
        "imgUrl": "/images/goods5.png",
        "amount": 876698
      },
      {
        "id": 7,
        "name": "Triple Berry Yogurt Delight",
        "imgUrl": "/images/goods7.png",
        "amount": 10223301
      },
      {
        "id": 9,
        "name": "Strawberry Panna Bliss",
        "imgUrl": "/images/goods9.png",
        "amount": 987373
      }
    ],
    "totalAmount": 18223301,
    "id": 1
  }
]
